llama_index/py.typed
llama_index/vector_stores/nile/__init__.py
llama_index/vector_stores/nile/base.py
llama_index_vector_stores_nile-0.3.1.dist-info/METADATA
llama_index_vector_stores_nile-0.3.1.dist-info/WHEEL
llama_index_vector_stores_nile-0.3.1.dist-info/licenses/LICENSE
llama_index_vector_stores_nile-0.3.1.dist-info/RECORD
